bffpostgres/__init__.py
bffpostgres/client.py
bffpostgres/utils.py
gqlbff_postgres-0.0.3.data/data/LICENSE
gqlbff_postgres-0.0.3.dist-info/LICENSE
gqlbff_postgres-0.0.3.dist-info/METADATA
gqlbff_postgres-0.0.3.dist-info/WHEEL
gqlbff_postgres-0.0.3.dist-info/top_level.txt
gqlbff_postgres-0.0.3.dist-info/RECORD
